{"relevantArticles":[{"articleTitle":"l2tp over ipsec添加用户登陆日志","articleAbstractText":"\u2003\u2003越长大越觉得，比起诉说自己的委屈与不甘，沉默最好。反正，你信你的，我活我的。","articleStatus":0,"articlePermalink":"/articles/2020/12/08/1607423165456.html","articleImg1URL":"https://b3logfile.com/bing/20180506.jpg?imageView2/1/w/1280/h/720/interlace/1/q/100"},{"articleTitle":"关于 Kubernetes 的这些原理，你一定要了解","articleAbstractText":"\u2003\u2003kubernetes 已经成为容器编排领域的王者，它是基于容器的集群编排引擎，具备扩展集群、滚动升级回滚、弹性伸缩、自动治愈、服务发现等多种特性能力。 \u2003\u2003本文将带着大家快速了解 kubernetes ，了解我们谈论 kubernetes 都是在谈论什么。 kubernetes 架构 \u2003\u2003 \u2003\u2003从宏观上来看 kubernetes 的整体架构，包括 Master、Node 以及 Etcd。 \u2003\u2003Master 即主节点，负责控制整个 kubernetes 集群。它包括 API Server、Scheduler、Controller 等组成部分。它们都需要和 Etcd 进行交互以存储数据。  API Server：主要提供资源操作的统一入口，这样就屏蔽了与 Etcd 的直接交互。功能包括安全、注册与发现等。 Scheduler：负责按照一定的调度规则将 Pod 调度到 Node 上。 Controller：资源控制中心，确保资源处于预期的工作状态。  \u2003\u2003Node 即工作节点，为整个集群提供计算力，是容器真正运行的地方，包括运行容器、kubelet、kube-proxy。  kubele....","articleStatus":0,"articlePermalink":"/articles/2020/08/15/1597459617030.html","articleImg1URL":"https://file.cjzshilong.cn/pictures_file/kubernetes-area.png?imageView2/1/w/1280/h/720/interlace/1/q/100"},{"articleTitle":"修改数据库名的一种方法","articleAbstractText":"\u2003\u2003海可以枯，石可以烂，我对你的爱，永不会变。","articleStatus":0,"articlePermalink":"/articles/2020/08/23/1598183218602.html","articleImg1URL":"https://b3logfile.com/bing/20200604.jpg?imageView2/1/w/1280/h/720/interlace/1/q/100"},{"articleTitle":"Kubernetes服务访问","articleAbstractText":"\u2003\u2003感情淡了我们再培养，无话可说了我们就再去找话题，觉得腻了我们就重新认识，要是累了就给彼此空间，人潮汹涌的遇到你也不容易，也不想再推开了。","articleStatus":0,"articlePermalink":"/articles/2020/04/23/1587624487440.html","articleImg1URL":"https://file.cjzshilong.cn/pictures_file/services-iptables-overview.svg?imageView2/1/w/1280/h/720/interlace/1/q/100"},{"articleTitle":"Haproxy","articleAbstractText":"Haproxy haproxy 配置文件 [root@ali-pro-ops-ldap_blance ~]# cat /usr/local/haproxy/conf/haproxy.cfg global log 127.0.0.1 local3 log 127.0.0.1 local1 notice stats timeout 30s uid 99 gid 99 daemon # nbproc 4 # chroot /usr/local/haproxy pidfile /usr/local/haproxy/run/haproxy.pid chroot /usr/local/haproxy defaults log global mode http option httplog option dontlognull timeout connect 5000 timeout client 50000 timeout server 50000 listen LDAP-10389 bind 0.0.0.0:10389 mode tcp option tcplog maxconn 2000 ti....","articleStatus":0,"articlePermalink":"/articles/2020/07/29/1596024607735.html","articleImg1URL":"https://b3logfile.com/file/2020/07/image-6b36d889.png?imageView2/2/w/1280/format/jpg/interlace/1/q/100"}]}